aodhclient/__init__.py
aodhclient/client.py
aodhclient/exceptions.py
aodhclient/i18n.py
aodhclient/noauth.py
aodhclient/osc.py
aodhclient/shell.py
aodhclient/utils.py
aodhclient/tests/__init__.py
aodhclient/tests/functional/__init__.py
aodhclient/tests/functional/base.py
aodhclient/tests/functional/test_alarm.py
aodhclient/tests/functional/test_alarm_history.py
aodhclient/tests/functional/test_capabilities.py
aodhclient/tests/functional/test_metrics.py
aodhclient/tests/unit/__init__.py
aodhclient/tests/unit/test_alarm_cli.py
aodhclient/tests/unit/test_alarm_history.py
aodhclient/tests/unit/test_alarm_manager.py
aodhclient/tests/unit/test_exceptions.py
aodhclient/tests/unit/test_metrics.py
aodhclient/tests/unit/test_quota.py
aodhclient/tests/unit/test_shell.py
aodhclient/tests/unit/test_utils.py
aodhclient/v2/__init__.py
aodhclient/v2/alarm.py
aodhclient/v2/alarm_cli.py
aodhclient/v2/alarm_history.py
aodhclient/v2/alarm_history_cli.py
aodhclient/v2/base.py
aodhclient/v2/capabilities.py
aodhclient/v2/capabilities_cli.py
aodhclient/v2/client.py
aodhclient/v2/metrics.py
aodhclient/v2/metrics_cli.py
aodhclient/v2/quota.py
aodhclient/v2/quota_cli.py
aodhclient-3.10.0.dist-info/licenses/AUTHORS
aodhclient-3.10.0.dist-info/licenses/LICENSE
aodhclient-3.10.0.dist-info/METADATA
aodhclient-3.10.0.dist-info/WHEEL
aodhclient-3.10.0.dist-info/entry_points.txt
aodhclient-3.10.0.dist-info/pbr.json
aodhclient-3.10.0.dist-info/top_level.txt
aodhclient-3.10.0.dist-info/RECORD
